{
  "accentColor": "{{appsmith.theme.colors.primaryColor}}",
  "allowDialCodeChange": false,
  "allowFormatting": false,
  "animateLoading": true,
  "autoFocus": false,
  "borderRadius": "{{appsmith.theme.borderRadius.appBorderRadius}}",
  "bottomRow": 63,
  "boxShadow": "none",
  "defaultDialCode": "+1664",
  "defaultText": "{{appsmith.store.cell}}",
  "displayName": "Phone Input",
  "dynamicBindingPathList": [
    {
      "key": "defaultText"
    },
    {
      "key": "accentColor"
    },
    {
      "key": "borderRadius"
    }
  ],
  "dynamicHeight": "FIXED",
  "dynamicPropertyPathList": [],
  "dynamicTriggerPathList": [],
  "hideCard": false,
  "iconAlign": "left",
  "iconSVG": "/static/media/icon.108789d7165de30306435ab3c24e6cad.svg",
  "isDeprecated": false,
  "isDisabled": false,
  "isLoading": false,
  "isRequired": false,
  "isVisible": true,
  "key": "3lpv64df30",
  "label": "Phone",
  "labelAlignment": "left",
  "labelPosition": "Left",
  "labelStyle": "",
  "labelTextSize": "0.875rem",
  "labelWidth": "3",
  "leftColumn": 0,
  "maxDynamicHeight": 9000,
  "minDynamicHeight": 4,
  "parentColumnSpace": 13.75,
  "parentId": "ijtgmtni2k",
  "parentRowSpace": 10,
  "renderMode": "CANVAS",
  "resetOnSubmit": true,
  "rightColumn": 20,
  "searchTags": [
    "call"
  ],
  "topRow": 59,
  "type": "PHONE_INPUT_WIDGET",
  "version": 1,
  "widgetId": "qppi9qtlwp",
  "widgetName": "PhoneInput2"
}